[
    {
        "name": "Below Zero",
        "link": "https://youtu.be/Olj5NkikjTQ",
        "comment": "Snow White's so cool."
    },
    {
        "name": "Extreme Tunnel Destroyer",
        "link": "https://youtu.be/24QsDf6ICD0",
        "comment": "It's either I'm playing Osu Standard or fighting Gravedigger. There's no inbetween!"
    },
    {
        "name": "Take My MONEY!!",
        "link": "https://youtu.be/irK68N3Lrrg",
        "comment": "Free credits, and buying SSR molds because I constantly get Rs and SRs from gacha. I love this shop."
    },
    {
        "name": "Marian",
        "link": "https://youtu.be/CrvloNIJACw",
        "comment": "I will not cry again. I won't."
    },
    {
        "name": "Khamsin",
        "link": "https://youtu.be/-rqACdYcnW8",
        "comment": "Where do we go from here?"
    },
    {
        "name": "Ominous Cross",
        "link": "https://youtu.be/qzuMp6E_fP0",
        "comment": "MARIANNNNNNNNNNNNNN!  COME BACKKK!!"
    },
    {
        "name": "The Harvester",
        "link": "https://youtu.be/xjQzdQIBDW0",
        "comment": "Heart is racing, here, now..."
    },
    {
        "name": "Slaughterer",
        "link": "https://youtu.be/E3tyzm6uZks",
        "comment": "The only thing they fear is us, truly."
    },
    {
        "name": "Hey Newbie",
        "link": "https://youtu.be/0V1cRgBtVSQ",
        "comment": ""
    },
    {
        "name": "Girl's Talk",
        "link": "https://youtu.be/_mdWZJ3RKLM",
        "comment": ""
    },
    {
        "name": "Disaster",
        "link": "https://youtu.be/POJHs0nLaeU",
        "comment": ""
    },
    {
        "name": "Counter Attack",
        "link": "https://youtu.be/YAxEv-O96dc",
        "comment": "There's nothing that I, could do..."
    },
    {
        "name": "The Calm Before The Storm",
        "link": "https://youtu.be/UlQnU7XfWUs",
        "comment": ""
    },
    {
        "name": "Risk",
        "link": "https://youtu.be/jKEbiPTVhFk",
        "comment": ""
    },
    {
        "name": "Recognition",
        "link": "https://youtu.be/xEezf5ratrk",
        "comment": ""
    },
    {
        "name": "Tempest",
        "link": "https://youtu.be/xQaXUZbb1ws",
        "comment": "I feel like a god."
    },
    {
        "name": "Maze in Abyss",
        "link": "https://youtu.be/wT9T0cN7aLk",
        "comment": "I'm confused."
    },
    {
        "name": "Labyrinth of Void",
        "link": "https://youtu.be/rVkBm4CzLNs",
        "comment": "Where do you want me to go? Here? What do you mean over there as well??"
    },
    {
        "name": "Meditation",
        "link": "https://youtu.be/hgaeqBjQkyQ",
        "comment": "The commander's room always has this playing 24/7."
    },
    {
        "name": "Hero",
        "link": "https://youtu.be/slhFNvxd8ms",
        "comment": ""
    },
    {
        "name": "Hero (Vocals)",
        "link": "https://youtu.be/6JOV8GqMRJU",
        "comment": ""
    },
    {
        "name": "Wings of Victory",
        "link": "https://youtu.be/zkXCn744jTg",
        "comment": ""
    },
    {
        "name": "Wings of Victory (Vocals)",
        "link": "https://youtu.be/dzB0E9_OojA",
        "comment": "Drift!"
    },
    {
        "name": "Broken Wings",
        "link": "https://youtu.be/Xsh4aFpATR0",
        "comment": ""
    },
    {
        "name": "Underwater Flowers",
        "link": "https://youtu.be/A0RR3rS4dhg",
        "comment": ""
    },
    {
        "name": "Resist",
        "link": "https://youtu.be/2DFFAO8XGXk",
        "comment": "Not the first time I've fought a structure of some sort."
    },
    {
        "name": "Black Gunsmoke",
        "link": "https://youtu.be/pgEBJdg0kOQ",
        "comment": ""
    },
    {
        "name": "Metal Acid",
        "link": "https://youtu.be/WmLanMSy4CA",
        "comment": ""
    },
    {
        "name": "Para-DICE",
        "link": "https://youtu.be/OKn4V3pDXT4",
        "comment": "One step forward, two steps back. Goddamnit Laplace..."
    },
    {
        "name": "Shape of Hope",
        "link": "https://youtu.be/l0WiViMdYRs",
        "comment": ""
    },
    {
        "name": "Chromosome",
        "link": "https://youtu.be/jLfIS8LA-yo",
        "comment": "skin tone, chicken bone, you have an extra..."
    },
    {
        "name": "Destined to Fight",
        "link": "https://youtu.be/59GPWsHc-mI",
        "comment": ""
    },
    {
        "name": "Marry Bad",
        "link": "https://youtu.be/09pmuSOfyRY",
        "comment": ""
    },
    {
        "name": "Bulletstorm",
        "link": "https://youtu.be/VRpkhNiEkWA",
        "comment": ""
    },
    {
        "name": "Tomboy Princess",
        "link": "https://youtu.be/8R7M5vLNvr8",
        "comment": ""
    },
    {
        "name": "YOU CAN'T STOP US",
        "link": "https://youtu.be/f4-5qG_ZH7Y",
        "comment": ""
    },
    {
        "name": "HOLY CRAB",
        "link": "https://youtu.be/2-qKb4vgj7M",
        "comment": "🦀 🦀 I HAVE NO MORE GEMS 🦀 🦀"
    },
    {
        "name": "BASS BOMB",
        "link": "https://youtu.be/2Lvhehm4Rmc",
        "comment": "🦀 🦀 🦀 🦀 🦀 🦀"
    },
    {
        "name": "It's VOLT TIME",
        "link": "https://youtu.be/gSEBWXT4-sE",
        "comment": "Let's just say this was better than the other one."
    },
    {
        "name": "WE RISE",
        "link": "https://youtu.be/LKAs-FqqCmo",
        "comment": "If only the internet wasn't so slow. I know this song by heart already!"
    },
    {
        "name": "DUST RIDER",
        "link": "https://youtu.be/g4i-mTmWLHg",
        "comment": ""
    },
    {
        "name": "Stronghold Land Eater",
        "link": "https://youtu.be/lSt_6SiAUwo",
        "comment": "BANGER"
    },
    {
        "name": "Lonely Lonely Cat",
        "link": "https://youtu.be/S-bOBwuBRdU",
        "comment": "lofi beats to cry on"
    },
    {
        "name": "The Goddess Fall",
        "link": "https://youtu.be/0t1pYScEXGA",
        "comment": "..."
    },
    {
        "name": "Artificial Shangri-La",
        "link": "https://youtu.be/7-QCz5erPKQ",
        "comment": "The sillies :smiling_face_with_3_hearts: :smiling_face_with_3_hearts: The sillies are walking :smiling_face_with_3_hearts:"
    }
]